tidy_vcf/__init__.py
tidy_vcf/tidy_vcf.py
tidy_vcf-0.1.2.3.dist-info/LICENSE
tidy_vcf-0.1.2.3.dist-info/METADATA
tidy_vcf-0.1.2.3.dist-info/WHEEL
tidy_vcf-0.1.2.3.dist-info/entry_points.txt
tidy_vcf-0.1.2.3.dist-info/top_level.txt
tidy_vcf-0.1.2.3.dist-info/RECORD
