Metadata-Version: 2.1
Name: tidy-vcf
Version: 0.1.2.3
Summary: Make tidy VCF data.
Home-page: https://github.com/silastittes/tidy_vcf
Author: Silas Tittes
Author-email: silas.tittes@gmail.com
License: MIT
Keywords: VCF genetics python package
Platform: UNKNOWN
Classifier: Programming Language :: Python :: 3
Classifier: License :: OSI Approved :: MIT License
Classifier: Operating System :: OS Independent
Requires-Python: >=3.6
